upscript/__init__.py
upscript/__main__.py
upscript/_cli.py
upscript/_internal_api.py
upscript/_scripts.py
upscript/_state.py
upscript/_update.py
upscript/_utils.py
upscript-0.2.0.dist-info/entry_points.txt
upscript-0.2.0.dist-info/WHEEL
upscript-0.2.0.dist-info/METADATA
upscript-0.2.0.dist-info/RECORD
